alino_package/__init__.py
alino_package/calcul.py
calcul_kemgue-0.0.1.dist-info/LICENSE
calcul_kemgue-0.0.1.dist-info/METADATA
calcul_kemgue-0.0.1.dist-info/WHEEL
calcul_kemgue-0.0.1.dist-info/top_level.txt
calcul_kemgue-0.0.1.dist-info/RECORD
