Metadata-Version: 2.1
Name: calcul-kemgue
Version: 0.0.1
Summary: Ce simple package permet de faire de simples calculs mathématique de base
Home-page: https://github.com/pypa/sampleproject
Author: Alain Kemgue
Author-email: kemguealain@yahoo.fr
License: MIT License
Project-URL: Bug Tracker, https://github.com/pypa/sampleproject/issues
Project-URL: Me Dire Bonjour, https://github.com/alino/bonjour
Platform: Toutes les plateforme qui utilise python
Classifier: Programming Language :: Python :: 3
Classifier: License :: OSI Approved :: MIT License
Classifier: Operating System :: OS Independent
Requires-Python: >=3.8
License-File: LICENSE
Requires-Dist: numpy (>=1.21.4)
Requires-Dist: pytest (>=6.2.5)
